idstools/__init__.py
idstools/_version.py
idstools/cocos.py
idstools/database.py
idstools/eqdsk2ids.py
idstools/idschk.py
idstools/idsperf.py
idstools/init_mendeleiev.py
idstools/input_processing.py
idstools/machinedescription.py
idstools/scenariodescription.py
idstools/set_logger.py
idstools/compute/__init__.py
idstools/compute/common.py
idstools/compute/core_profiles.py
idstools/compute/core_sources.py
idstools/compute/core_transport.py
idstools/compute/distribution_sources.py
idstools/compute/distributions.py
idstools/compute/edge_profiles.py
idstools/compute/equilibrium.py
idstools/compute/magnetics.py
idstools/compute/pf_active.py
idstools/compute/pf_passive.py
idstools/compute/spectrometer_visible.py
idstools/compute/summary.py
idstools/compute/tf.py
idstools/compute/wall.py
idstools/compute/waves.py
idstools/domain/__init__.py
idstools/domain/ecstray.py
idstools/domain/kineticprofiles.py
idstools/test/idstools_tests/__init__.py
idstools/test/idstools_tests/compute/__init__.py
idstools/test/idstools_tests/compute/common/__init__.py
idstools/test/idstools_tests/compute/common/test_functions.py
idstools/utils/__init__.py
idstools/utils/clihelper.py
idstools/utils/idshelper.py
idstools/utils/idslogger.py
idstools/utils/utility_functions.py
idstools/view/__init__.py
idstools/view/common.py
idstools/view/core_profiles.py
idstools/view/core_sources.py
idstools/view/core_transport.py
idstools/view/distribution_sources.py
idstools/view/distributions.py
idstools/view/edge_profiles.py
idstools/view/equilibrium.py
idstools/view/magnetics.py
idstools/view/pf_active.py
idstools/view/pf_passive.py
idstools/view/polygon.py
idstools/view/spectrometer_visible.py
idstools/view/summary.py
idstools/view/tf.py
idstools/view/wall.py
idstools/view/waves.py
idstools/view/domain/__init__.py
idstools/view/domain/ecstray.py
idstools/view/domain/kineticprofiles.py
idstools/view/domain/mdplot.py
idstools/view/styles/scientific.mplstyle
imas_idstools-2.4.0.data/data/bin/create_db_entry
imas_idstools-2.4.0.dist-info/licenses/LICENSE.md
imas_idstools-2.4.0.dist-info/METADATA
imas_idstools-2.4.0.dist-info/WHEEL
imas_idstools-2.4.0.dist-info/top_level.txt
imas_idstools-2.4.0.dist-info/RECORD
