Metadata-Version: 2.4
Name: imas-idstools
Version: 2.4.0
Summary: Python based collection of data analysis and visualization tools written in IMAS framework
Author-email: ITER Organization <imas-support@iter.org>
Project-URL: homepage, https://git.iter.org/projects/IMAS/repos/idstools/browse
Keywords: IMAS,IDS
Classifier: Development Status :: 5 - Production/Stable
Classifier: Environment :: Console
Classifier: Environment :: Plugins
Classifier: Environment :: X11 Applications
Classifier: Framework :: Flake8
Classifier: Framework :: IPython
Classifier: Framework :: Matplotlib
Classifier: Framework :: Pytest
Classifier: Framework :: Sphinx
Classifier: Intended Audience :: Developers
Classifier: Intended Audience :: Science/Research
Classifier: Intended Audience :: System Administrators
Classifier: Natural Language :: English
Classifier: Operating System :: POSIX
Classifier: Operating System :: POSIX :: Linux
Classifier: Programming Language :: Python
Classifier: Programming Language :: Python :: 3
Classifier: Programming Language :: Python :: 3.8
Classifier: Programming Language :: Python :: 3.9
Classifier: Programming Language :: Unix Shell
Classifier: Topic :: Database
Classifier: Topic :: Database :: Front-Ends
Classifier: Topic :: Scientific/Engineering
Classifier: Topic :: Scientific/Engineering :: Physics
Classifier: Topic :: Scientific/Engineering :: Visualization
Classifier: Topic :: Software Development :: Libraries
Classifier: Topic :: Software Development :: Libraries :: Python Modules
Classifier: Topic :: System
Classifier: Topic :: System :: Software Distribution
Classifier: Topic :: Utilities
Requires-Python: >=3.8
License-File: LICENSE.md
Requires-Dist: cerberus
Requires-Dist: fortranformat
Requires-Dist: imas-python
Requires-Dist: matplotlib
Requires-Dist: netCDF4
Requires-Dist: numpy
Requires-Dist: packaging
Requires-Dist: pandas
Requires-Dist: pyparsing
Requires-Dist: python-dateutil
Requires-Dist: pyyaml
Requires-Dist: rich
Requires-Dist: rich_argparse
Requires-Dist: six
Requires-Dist: tabulate
Provides-Extra: all
Requires-Dist: imas-idstools[docs,test]; extra == "all"
Provides-Extra: docs
Requires-Dist: sphinx<7.0.0,>=6.0.0; extra == "docs"
Requires-Dist: numpy; extra == "docs"
Requires-Dist: pyparsing; extra == "docs"
Requires-Dist: python-dateutil; extra == "docs"
Requires-Dist: rst2pdf; extra == "docs"
Requires-Dist: sphinx-autoapi; extra == "docs"
Requires-Dist: sphinx-autodoc-typehints; extra == "docs"
Requires-Dist: sphinx-immaterial<0.12,>0.11.0; extra == "docs"
Requires-Dist: sphinx-toolbox; extra == "docs"
Requires-Dist: sphinxcontrib-programoutput; extra == "docs"
Requires-Dist: click; extra == "docs"
Requires-Dist: setuptools-scm; extra == "docs"
Provides-Extra: test
Requires-Dist: pytest; extra == "test"
Requires-Dist: pytest-cov; extra == "test"
Requires-Dist: pytest-xdist; extra == "test"
Dynamic: license-file
